Metadata-Version: 1.1
Name: geek-translate
Version: 0.7.0
Summary: sogou
Home-page: https://github.com/mydu27/deemo
Author: chen
Author-email: chenjiageng@geekpark.net
License: UNKNOWN
Platform: UNKNOWN
Classifier: Programming Language :: Python
Classifier: Intended Audience :: Developers
